CHANGELOG
LICENSE
MANIFEST.in
README.rst
setup.py
django_locksmith.egg-info/PKG-INFO
django_locksmith.egg-info/SOURCES.txt
django_locksmith.egg-info/dependency_links.txt
django_locksmith.egg-info/top_level.txt
locksmith/__init__.py
locksmith/common.py
locksmith/auth/__init__.py
locksmith/auth/admin.py
locksmith/auth/authentication.py
locksmith/auth/middleware.py
locksmith/auth/models.py
locksmith/auth/urls.py
locksmith/auth/views.py
locksmith/auth/management/__init__.py
locksmith/auth/management/commands/__init__.py
locksmith/auth/management/commands/apireport.py
locksmith/auth/management/commands/resetkeys.py
locksmith/hub/__init__.py
locksmith/hub/admin.py
locksmith/hub/auth_backend.py
locksmith/hub/common.py
locksmith/hub/dataviews.py
locksmith/hub/models.py
locksmith/hub/tasks.py
locksmith/hub/urls.py
locksmith/hub/views.py
locksmith/hub/management/__init__.py
locksmith/hub/management/commands/__init__.py
locksmith/hub/management/commands/pushkeys.py
locksmith/hub/management/commands/reportaggregates.py
locksmith/hub/migrations/0001_initial.py
locksmith/hub/migrations/0002_auto__git_commit_14a8cadceb.py
locksmith/hub/migrations/0003_auto__add_unique_key_email.py
locksmith/hub/migrations/0004_auto__add_field_key_user__add_field_key_alternate_email__add_field_key.py
locksmith/hub/migrations/0005_auto__add_field_api_querybuilder_link.py
locksmith/hub/migrations/0006_auto__chg_field_key_org_url__chg_field_key_usage.py
locksmith/hub/migrations/0007_auto__add_field_api_status_message.py
locksmith/hub/migrations/0008_auto__add_field_api_tools_text.py
locksmith/hub/migrations/0009_auto.py
locksmith/hub/migrations/__init__.py
locksmith/hub/templates/locksmith/analytics_index.html
locksmith/hub/templates/locksmith/api_analytics.html
locksmith/hub/templates/locksmith/base.html
locksmith/hub/templates/locksmith/confirmed.html
locksmith/hub/templates/locksmith/key_analytics.html
locksmith/hub/templates/locksmith/key_analytics_unauthorized.html
locksmith/hub/templates/locksmith/key_edit.html
locksmith/hub/templates/locksmith/keys_list.html
locksmith/hub/templates/locksmith/leaderboard.html
