Metadata-Version: 1.0
Name: django-locksmith
Version: 0.8.0
Summary: Django apps for API authentication and centralized authorization
Home-page: http://github.com/sunlightlabs/django-locksmith/
Author: James Turk
Author-email: jturk@sunlightfoundation.com
License: BSD
Platform: UNKNOWN
